myoldpackageula/__init__.py
myoldpackageula/numbers/__init__.py
myoldpackageula/numbers/digits.py
myoldpackageula-0.1.0.dist-info/METADATA
myoldpackageula-0.1.0.dist-info/WHEEL
myoldpackageula-0.1.0.dist-info/RECORD
