Metadata-Version: 2.1
Name: myoldpackageula
Version: 0.1.0
Summary: 
Author: Ula
Author-email: ula.malin35@gmail.com
Requires-Python: >=3.12,<4.0
Classifier: Programming Language :: Python :: 3
Classifier: Programming Language :: Python :: 3.12
Requires-Dist: pytest (>=8.0.2,<9.0.0)
